gogo_gadget/__init__.py
gogo_gadget/cli.py
gogo_gadget/config.py
gogo_gadget-0.2.5.dist-info/LICENSE
gogo_gadget-0.2.5.dist-info/METADATA
gogo_gadget-0.2.5.dist-info/WHEEL
gogo_gadget-0.2.5.dist-info/entry_points.txt
gogo_gadget-0.2.5.dist-info/top_level.txt
gogo_gadget-0.2.5.dist-info/RECORD
