Metadata-Version: 2.1
Name: gogo-gadget
Version: 0.2.5
Summary: A tool to aggregate custom command line tools into one
Home-page: https://github.com/ratschlab/tools-gogo-gadget
Author: Marc Zimmermann
Author-email: marc.zimmermann@inf.ethz.ch
License: MIT license
Keywords: gogo-gadget
Platform: UNKNOWN
Classifier: Development Status :: 2 - Pre-Alpha
Classifier: Intended Audience :: Developers
Classifier: License :: OSI Approved :: MIT License
Classifier: Natural Language :: English
Classifier: Programming Language :: Python :: 3
Classifier: Programming Language :: Python :: 3.4
Classifier: Programming Language :: Python :: 3.5
Classifier: Programming Language :: Python :: 3.6
Requires-Dist: Click (<8.0,>=7.0)
Requires-Dist: pyyaml (>=4.2b1)
